clyjin/__init__.py
clyjin/__main__.py
clyjin/base/__init__.py
clyjin/base/config.py
clyjin/base/errors.py
clyjin/base/model.py
clyjin/base/module.py
clyjin/base/moduleargs.py
clyjin/base/moduledata.py
clyjin/base/plugin.py
clyjin/base/plugininitializedata.py
clyjin/core/__init__.py
clyjin/core/boot.py
clyjin/core/cli/__init__.py
clyjin/core/cli/cliargs.py
clyjin/core/cli/generator.py
clyjin/core/cli/parser.py
clyjin/core/plugin/__init__.py
clyjin/core/plugin/args.py
clyjin/core/plugin/modules.py
clyjin/core/plugin/plugin.py
clyjin/core/test_boot.py
clyjin/log.py
clyjin/utils/__init__.py
clyjin/utils/string.py
clyjin/utils/types.py
clyjin-0.2.12.dist-info/LICENSE
clyjin-0.2.12.dist-info/METADATA
clyjin-0.2.12.dist-info/WHEEL
clyjin-0.2.12.dist-info/entry_points.txt
clyjin-0.2.12.dist-info/RECORD
