Metadata-Version: 2.1
Name: clyjin
Version: 0.2.12
Summary: Core for building plugins with CLI interfaces
Home-page: https://github.com/ryzhovalex/clyjin
License: MIT
Keywords: toolbox,cli,plugin,custom
Author: ryzhovalex
Author-email: thed4rkof@gmail.com
Requires-Python: >=3.11,<4.0
Classifier: License :: OSI Approved :: MIT License
Classifier: Programming Language :: Python :: 3
Classifier: Programming Language :: Python :: 3.11
Requires-Dist: aiofiles (>=23.2.1,<24.0.0)
Requires-Dist: antievil (>=0.1.4,<0.2.0)
Requires-Dist: loguru (>=0.7.0,<0.8.0)
Requires-Dist: pydantic (>=2.1.1,<3.0.0)
Requires-Dist: python-dotenv (>=1.0.0,<2.0.0)
Requires-Dist: pyyaml (>=6.0.1,<7.0.0)
Project-URL: Repository, https://github.com/ryzhovalex/clyjin
